UOFast/__init__.py
UOFast/main.py
UOFast/UOClasses/UOClassInitiator.py
UOFast/UOClasses/UOFastConfig.py
UOFast/UOClasses/UOFastDataArray.py
UOFast/UOClasses/UOFastDataArray_dep.py
UOFast/UOClasses/UOLoader.py
UOFast/UOClasses/__init__.py
UOFast/gsocketpool/__init__.py
UOFast/gsocketpool/connection.py
UOFast/gsocketpool/exceptions.py
UOFast/gsocketpool/pool.py
uofast-0.1.35.dist-info/LICENSE
uofast-0.1.35.dist-info/WHEEL
uofast-0.1.35.dist-info/METADATA
uofast-0.1.35.dist-info/RECORD
