Metadata-Version: 2.1
Name: UOFast
Version: 0.1.35
Summary: UOFast is a U2 UOPY based restful service which pools U2 UOPY connections and accepts GET/PUT type requests 
Author-email: "RokiPark (c) Kurt Konchadi 2023" <tech@rokipark.ai>
Requires-Python: >=3.9
Classifier: License :: OSI Approved :: MIT License
Requires-Dist: fastapi==0.100.1
Requires-Dist: uvicorn
Requires-Dist: gsocketpool
Requires-Dist: gevent
Requires-Dist: greenlet
Requires-Dist: pydantic
Requires-Dist: requests
Requires-Dist: uopy
Requires-Dist: langchain
Requires-Dist: langchain_community
Project-URL: Home, https://github.com/RoKiPaRk/UOFast
Project-URL: Web, http://rokipark.ai
